threadfluent/__init__.py
threadfluent/fluent.py
threadfluent/threadfluent.py
threadfluent/winssl.py
threadfluent-0.1.dist-info/METADATA
threadfluent-0.1.dist-info/WHEEL
threadfluent-0.1.dist-info/entry_points.txt
threadfluent-0.1.dist-info/top_level.txt
threadfluent-0.1.dist-info/RECORD
