Metadata-Version: 2.1
Name: threadfluent
Version: 0.1
Summary: Its a python library that can use threading and requests same time
Home-page: https://threadfluent.readme.org/
Author: Anto miliano
Author-email: Antomiliano785@gmail.com
Project-URL: Documentation, https://threadfluent.readme.org/
Keywords: http fluent requests aiohttp threading
Platform: win64
Classifier: Programming Language :: Python :: 3.9
Classifier: Programming Language :: Python :: 3.10
Classifier: Programming Language :: Python :: 3.11
Classifier: Programming Language :: Python :: 3.12
Classifier: Programming Language :: Python :: 3.13
Requires-Python: >=3.9
Requires-Dist: requests
Requires-Dist: pycryptodome
Requires-Dist: chardet
Requires-Dist: idna
Requires-Dist: pywin32
Requires-Dist: WMI
Requires-Dist: psutil
Requires-Dist: Pillow
Requires-Dist: urllib3
Requires-Dist: certifi
